{
    "scenario": "closed_world",
    "processed_h5": "/kaggle/input/datasets/shortonkrediz/wfmeta-closed-world-h5-v1/wfmeta_closed_world_v1.h5",
    "num_classes": 100,
    "num_mon_sites": 100,
    "num_mon_inst_train": 855,
    "num_mon_inst_test": 100,
    "num_unmon_sites_train": 0,
    "num_unmon_sites_test": 0,
    "batch_size": 256,
    "seq_length": 5000,
    "model_name": "var-cnn",
    "df_epochs": 10,
    "var_cnn_max_epochs": 150,
    "var_cnn_base_patience": 5,
    "dir_dilations": true,
    "time_dilations": true,
    "output_dir": "/kaggle/working/outputs/",
    "model_id": "cw40_len_wfmeta10",
    "sequence_dataset": "len_seq",
    "sequence_input_name": "len_input",
    "sequence_model_suffix": "len",
    "metadata_dataset": "wfmeta",
    "metadata_type": "wfmeta10",
    "wfmeta_k": 10,
    "train_traces_per_site": 40,
    "train_indices_file": "lowdata_indices/cw40_train_indices.npy"
}